{
  "mode": "hhcw",
  "tungsura": {
    "chart": {
      "1000005": 0,
      "1000006": 0,
      "progres": {
        "total": 10846,
        "persen": 99.82,
        "progres": 10826
      }
    },
    "table": {
      "1301": {
        "psu": "Reguler",
        "1000005": 0,
        "1000006": 0,
        "progres": {
          "total": 1042,
          "persen": 100.0,
          "progres": 1042
        },
        "status_progress": true
      },
      "1302": {
        "psu": "Reguler",
        "1000005": 0,
        "1000006": 0,
        "progres": {
          "total": 909,
          "persen": 100.0,
          "progres": 909
        },
        "status_progress": true
      },
      "1303": {
        "psu": "Reguler",
        "1000005": 0,
        "1000006": 0,
        "progres": {
          "total": 445,
          "persen": 100.0,
          "progres": 445
        },
        "status_progress": true
      },
      "1304": {
        "psu": "Reguler",
        "1000005": 0,
        "1000006": 0,
        "progres": {
          "total": 845,
          "persen": 100.0,
          "progres": 845
        },
        "status_progress": true
      },
      "1305": {
        "psu": "Reguler",
        "1000005": 0,
        "1000006": 0,
        "progres": {
          "total": 845,
          "persen": 100.0,
          "progres": 845
        },
        "status_progress": true
      },
      "1306": {
        "psu": "Reguler",
        "1000005": 0,
        "1000006": 0,
        "progres": {
          "total": 1211,
          "persen": 100.0,
          "progres": 1211
        },
        "status_progress": true
      },
      "1307": {
        "psu": "Reguler",
        "1000005": 0,
        "1000006": 0,
        "progres": {
          "total": 637,
          "persen": 100.0,
          "progres": 637
        },
        "status_progress": true
      },
      "1308": {
        "psu": "Reguler",
        "1000005": 0,
        "1000006": 0,
        "progres": {
          "total": 605,
          "persen": 100.0,
          "progres": 605
        },
        "status_progress": true
      },
      "1309": {
        "psu": "Reguler",
        "1000005": 0,
        "1000006": 0,
        "progres": {
          "total": 261,
          "persen": 93.1,
          "progres": 243
        },
        "status_progress": true
      },
      "1310": {
        "psu": "Reguler",
        "1000005": 0,
        "1000006": 0,
        "progres": {
          "total": 416,
          "persen": 100.0,
          "progres": 416
        },
        "status_progress": true
      },
      "1311": {
        "psu": "Reguler",
        "1000005": 0,
        "1000006": 0,
        "progres": {
          "total": 356,
          "persen": 100.0,
          "progres": 356
        },
        "status_progress": true
      },
      "1312": {
        "psu": "Reguler",
        "1000005": 0,
        "1000006": 0,
        "progres": {
          "total": 893,
          "persen": 99.89,
          "progres": 892
        },
        "status_progress": true
      },
      "1371": {
        "psu": "Reguler",
        "1000005": 0,
        "1000006": 0,
        "progres": {
          "total": 1487,
          "persen": 100.0,
          "progres": 1487
        },
        "status_progress": true
      },
      "1372": {
        "psu": "Reguler",
        "1000005": 0,
        "1000006": 0,
        "progres": {
          "total": 118,
          "persen": 99.15,
          "progres": 117
        },
        "status_progress": true
      },
      "1373": {
        "psu": "Reguler",
        "1000005": 0,
        "1000006": 0,
        "progres": {
          "total": 111,
          "persen": 100.0,
          "progres": 111
        },
        "status_progress": true
      },
      "1374": {
        "psu": "Reguler",
        "1000005": 0,
        "1000006": 0,
        "progres": {
          "total": 96,
          "persen": 100.0,
          "progres": 96
        },
        "status_progress": true
      },
      "1375": {
        "psu": "Reguler",
        "1000005": 0,
        "1000006": 0,
        "progres": {
          "total": 206,
          "persen": 100.0,
          "progres": 206
        },
        "status_progress": true
      },
      "1376": {
        "psu": "Reguler",
        "1000005": 0,
        "1000006": 0,
        "progres": {
          "total": 200,
          "persen": 100.0,
          "progres": 200
        },
        "status_progress": true
      },
      "1377": {
        "psu": "Reguler",
        "1000005": 0,
        "1000006": 0,
        "progres": {
          "total": 163,
          "persen": 100.0,
          "progres": 163
        },
        "status_progress": true
      }
    }
  },
  "psu": "Reguler",
  "progres": {
    "total": 10846,
    "progres": 10826
  },
  "ts": "2024-11-28 21:45:00"
}