{
  "mode": "hhcw",
  "tungsura": {
    "chart": {
      "1000007": 0,
      "1000008": 0,
      "1000009": 0,
      "progres": {
        "total": 11480,
        "persen": 99.53,
        "progres": 11426
      }
    },
    "table": {
      "1401": {
        "psu": "Reguler",
        "1000007": 0,
        "1000008": 0,
        "1000009": 0,
        "progres": {
          "total": 1280,
          "persen": 100.0,
          "progres": 1280
        },
        "status_progress": true
      },
      "1402": {
        "psu": "Reguler",
        "1000007": 0,
        "1000008": 0,
        "1000009": 0,
        "progres": {
          "total": 853,
          "persen": 99.65,
          "progres": 850
        },
        "status_progress": true
      },
      "1403": {
        "psu": "Reguler",
        "1000007": 0,
        "1000008": 0,
        "1000009": 0,
        "progres": {
          "total": 1154,
          "persen": 99.91,
          "progres": 1153
        },
        "status_progress": true
      },
      "1404": {
        "psu": "Reguler",
        "1000007": 0,
        "1000008": 0,
        "1000009": 0,
        "progres": {
          "total": 1558,
          "persen": 97.95,
          "progres": 1526
        },
        "status_progress": true
      },
      "1405": {
        "psu": "Reguler",
        "1000007": 0,
        "1000008": 0,
        "1000009": 0,
        "progres": {
          "total": 618,
          "persen": 100.0,
          "progres": 618
        },
        "status_progress": true
      },
      "1406": {
        "psu": "Reguler",
        "1000007": 0,
        "1000008": 0,
        "1000009": 0,
        "progres": {
          "total": 1151,
          "persen": 99.83,
          "progres": 1149
        },
        "status_progress": true
      },
      "1407": {
        "psu": "Reguler",
        "1000007": 0,
        "1000008": 0,
        "1000009": 0,
        "progres": {
          "total": 1147,
          "persen": 99.56,
          "progres": 1142
        },
        "status_progress": true
      },
      "1408": {
        "psu": "Reguler",
        "1000007": 0,
        "1000008": 0,
        "1000009": 0,
        "progres": {
          "total": 829,
          "persen": 99.88,
          "progres": 828
        },
        "status_progress": true
      },
      "1409": {
        "psu": "Reguler",
        "1000007": 0,
        "1000008": 0,
        "1000009": 0,
        "progres": {
          "total": 608,
          "persen": 99.67,
          "progres": 606
        },
        "status_progress": true
      },
      "1410": {
        "psu": "Reguler",
        "1000007": 0,
        "1000008": 0,
        "1000009": 0,
        "progres": {
          "total": 368,
          "persen": 99.73,
          "progres": 367
        },
        "status_progress": true
      },
      "1471": {
        "psu": "Reguler",
        "1000007": 0,
        "1000008": 0,
        "1000009": 0,
        "progres": {
          "total": 1389,
          "persen": 99.86,
          "progres": 1387
        },
        "status_progress": true
      },
      "1472": {
        "psu": "Reguler",
        "1000007": 0,
        "1000008": 0,
        "1000009": 0,
        "progres": {
          "total": 525,
          "persen": 99.05,
          "progres": 520
        },
        "status_progress": true
      }
    }
  },
  "psu": "Reguler",
  "progres": {
    "total": 11480,
    "progres": 11426
  },
  "ts": "2024-11-28 23:15:00"
}